mittn/__init__.py
mittn/headlessscanner/__init__.py
mittn/headlessscanner/dbtools.py
mittn/headlessscanner/proxy_comms.py
mittn/headlessscanner/steps.py
mittn/headlessscanner/test_dbtools.py
mittn/httpfuzzer/__init__.py
mittn/httpfuzzer/dbtools.py
mittn/httpfuzzer/dictwalker.py
mittn/httpfuzzer/fuzzer.py
mittn/httpfuzzer/httptools.py
mittn/httpfuzzer/injector.py
mittn/httpfuzzer/number_ranges.py
mittn/httpfuzzer/posttools.py
mittn/httpfuzzer/static_anomalies.py
mittn/httpfuzzer/steps.py
mittn/httpfuzzer/test_dbtools.py
mittn/httpfuzzer/url_params.py
mittn/tlschecker/__init__.py
mittn/tlschecker/steps.py
mittn-0.2.0.dist-info/DESCRIPTION.rst
mittn-0.2.0.dist-info/METADATA
mittn-0.2.0.dist-info/RECORD
mittn-0.2.0.dist-info/WHEEL
mittn-0.2.0.dist-info/metadata.json
mittn-0.2.0.dist-info/top_level.txt
