Metadata-Version: 2.0
Name: mittn
Version: 0.2.0
Summary: Mittn
Home-page: https://github.com/F-Secure/mittn
Author: F-Secure Corporation
Author-email: opensource@f-secure.com
License: Apache License 2.0
Platform: UNKNOWN
Classifier: Programming Language :: Python :: 2.7
Requires-Dist: SQLAlchemy (==0.9.8)
Requires-Dist: behave (>=1.2.4)
Requires-Dist: python-dateutil (>=2.2)
Requires-Dist: pytz (>=2014.2)
Requires-Dist: requests (>=2.2.1)
Requires-Dist: urlparse2 (>=1.1.1)
